positron_cli/__init__.py
positron_cli/cli.py
positron_cli/login.py
positron_cli/run_job.py
positron_common/__init__.py
positron_common/build_env
positron_common/build_env.py
positron_common/cli_args.py
positron_common/config.py
positron_common/deploy.py
positron_common/enums.py
positron_common/env_config.py
positron_common/env_defaults.py
positron_common/user_config.py
positron_common/utils.py
positron_common/job_api/__init__.py
positron_common/job_api/create_job.py
positron_job_runner/__init__.py
positron_job_runner/cli.py
positron_job_runner/run_job.py
positron_networks/__init__.py
positron_networks/decorator.py
positron_networks-0.1.14.dist-info/LICENSE
positron_networks-0.1.14.dist-info/METADATA
positron_networks-0.1.14.dist-info/WHEEL
positron_networks-0.1.14.dist-info/entry_points.txt
positron_networks-0.1.14.dist-info/top_level.txt
positron_networks-0.1.14.dist-info/RECORD
