Metadata-Version: 2.1
Name: positron_networks
Version: 0.1.14
Summary: Run experiments on the Positron Cloud
Author: Balint Kerdi
Author-email: bkerdi@positronnetworks.com
License: Apache License 2.0
Classifier: Programming Language :: Python :: 3
Classifier: License :: OSI Approved :: Apache Software License
Classifier: Operating System :: OS Independent
Requires-Python: >=3.6
License-File: LICENSE
Requires-Dist: requests <3.0.0,>=2.20.0
Requires-Dist: python-socketio <6.0.0,>=5.0.0
Requires-Dist: colorama <1.0.0,>=0.4.0
Requires-Dist: configparser <7.0.0,>=5.0.0
Requires-Dist: argparse >=1.4.0
Requires-Dist: aiohttp >=3.7.4.post0
Requires-Dist: typer >=0.12.3
Requires-Dist: pyyaml >=6.0.1
Requires-Dist: pydantic >=2.8.0
Requires-Dist: pydantic-core >=2.20.0
Requires-Dist: s3transfer >=0.10.0
Requires-Dist: boto3 >=1.34.0
